txt2ebook/__init__.py
txt2ebook/__main__.py
txt2ebook/cli.py
txt2ebook/exceptions.py
txt2ebook/parser.py
txt2ebook/tokenizer.py
txt2ebook/formats/__init__.py
txt2ebook/formats/base.py
txt2ebook/formats/epub.py
txt2ebook/formats/gmi.py
txt2ebook/formats/md.py
txt2ebook/formats/pdf.py
txt2ebook/formats/tex.py
txt2ebook/formats/txt.py
txt2ebook/formats/typ.py
txt2ebook/formats/templates/__init__.py
txt2ebook/formats/templates/epub/__init__.py
txt2ebook/helpers/__init__.py
txt2ebook/languages/__init__.py
txt2ebook/languages/en.py
txt2ebook/languages/zh_base.py
txt2ebook/languages/zh_cn.py
txt2ebook/languages/zh_tw.py
txt2ebook/models/__init__.py
txt2ebook/models/book.py
txt2ebook/models/chapter.py
txt2ebook/models/metadata.py
txt2ebook/models/paragraph.py
txt2ebook/models/volume.py
txt2ebook/subcommands/__init__.py
txt2ebook/subcommands/env.py
txt2ebook/subcommands/epub.py
txt2ebook/subcommands/gmi.py
txt2ebook/subcommands/massage.py
txt2ebook/subcommands/md.py
txt2ebook/subcommands/parse.py
txt2ebook/subcommands/pdf.py
txt2ebook/subcommands/tex.py
txt2ebook/subcommands/typ.py
txt2ebook-0.1.177.dist-info/licenses/LICENSE.md
txt2ebook-0.1.177.dist-info/METADATA
txt2ebook-0.1.177.dist-info/WHEEL
txt2ebook-0.1.177.dist-info/entry_points.txt
txt2ebook-0.1.177.dist-info/top_level.txt
txt2ebook-0.1.177.dist-info/RECORD
