Metadata-Version: 2.4
Name: txt2ebook
Version: 0.1.177
Summary: CLI tool to convert txt file to ebook format
Author-email: Kian-Meng Ang <kianmeng@cpan.org>
License-Expression: AGPL-3.0-or-later
Project-URL: Homepage, https://github.com/kianmeng/txt2ebook
Project-URL: Repository, https://github.com/kianmeng/txt2ebook
Keywords: cjk,ebook,epub,gmi,latex,md,pdf,txt,typst
Classifier: Development Status :: 4 - Beta
Classifier: Environment :: Console
Classifier: Natural Language :: Chinese (Simplified)
Classifier: Natural Language :: Chinese (Traditional)
Classifier: Programming Language :: Python
Classifier: Programming Language :: Python :: 3 :: Only
Classifier: Programming Language :: Python :: 3.10
Classifier: Programming Language :: Python :: 3.11
Classifier: Programming Language :: Python :: 3.12
Classifier: Programming Language :: Python :: 3.13
Classifier: Programming Language :: Python :: 3.14
Classifier: Topic :: Text Processing
Classifier: Topic :: Text Processing :: Filters
Classifier: Topic :: Text Processing :: General
Classifier: Topic :: Text Processing :: Markup :: HTML
Classifier: Topic :: Text Processing :: Markup :: Markdown
Requires-Python: >=3.10
License-File: LICENSE.md
Requires-Dist: CJKwrap~=2.2
Requires-Dist: EbookLib<0.18,>=0.17.1
Requires-Dist: beautifulsoup4>=4.12.0
Requires-Dist: importlib-resources<7,>=6.1.1
Requires-Dist: jieba<0.43,>=0.42.1
Requires-Dist: langdetect<2,>=1.0.9
Requires-Dist: lxml<6,>=5.2.2
Requires-Dist: pylatex<2,>=1.4.2
Requires-Dist: pypandoc~=1.11
Requires-Dist: regex>=2024.01.01
Requires-Dist: reportlab<5,>=4.0.0
Requires-Dist: typing-extensions<5,>=4.5.0
Requires-Dist: typst>=0.13.0
Provides-Extra: test
Requires-Dist: pytest; extra == "test"
Requires-Dist: pytest-cov; extra == "test"
Requires-Dist: pytest-randomly; extra == "test"
Requires-Dist: pytest-xdist; extra == "test"
Requires-Dist: scripttest; extra == "test"
Provides-Extra: doc
Requires-Dist: myst-parser; extra == "doc"
Requires-Dist: sphinx; extra == "doc"
Requires-Dist: sphinx-autobuild; extra == "doc"
Requires-Dist: sphinx-autodoc-typehints; extra == "doc"
Requires-Dist: sphinx-copybutton; extra == "doc"
Provides-Extra: pot
Requires-Dist: Babel; extra == "pot"
Provides-Extra: lint
Requires-Dist: pre-commit; extra == "lint"
Requires-Dist: ruff; extra == "lint"
Requires-Dist: mypy; extra == "lint"
Dynamic: license-file
